libOrbbecSDK.so
libOrbbecSDK.so.1.10
libOrbbecSDK.so.1.10.16
libdepthengine.so
libdepthengine.so.2.0
liblive555.so
libob_usb.so
pyorbbecsdk.cpython-312-x86_64-linux-gnu.so
pyorbbecsdk/pyorbbecsdk.pyi
pyorbbecsdk_community-1.4.2.dist-info/licenses/LICENSE
pyorbbecsdk_community-1.4.2.dist-info/METADATA
pyorbbecsdk_community-1.4.2.dist-info/WHEEL
pyorbbecsdk_community-1.4.2.dist-info/top_level.txt
pyorbbecsdk_community-1.4.2.dist-info/RECORD
