Metadata-Version: 2.1
Name: pyorbbecsdk-community
Version: 1.4.2
Summary: pyorbbecsdk-community is a community-maintained python wrapper for the OrbbecSDK
Author-email: Joe Dong <mocun@orbbec.com>, William Yan <pypi@xinan-yan.com>
Project-URL: Homepage, https://github.com/W-YXN/pyorbbecsdk
Project-URL: Bug Tracker, https://github.com/W-YXN/pyorbbecsdk/issues
Classifier: Programming Language :: Python :: 3
Requires-Python: >=3.7
License-File: LICENSE
Requires-Dist: numpy
Requires-Dist: opencv-python
Requires-Dist: plyfile
Requires-Dist: open3d
Requires-Dist: av
Requires-Dist: pygame
